{
  "address": "_REQUESTED_",
  "location": "_REQUESTED_",
  "part of town": "_REQUESTED_",
  "located": "_REQUESTED_",
  "area": "_REQUESTED_",
  "part": "_REQUESTED_",
  "kind of food": "_REQUESTED_",
  "cuisine type": "_REQUESTED_",
  "type of cuisine": "_REQUESTED_",
  "kind of dishes": "_REQUESTED_",
  "type of food": "_REQUESTED_",
  "food": "_REQUESTED_",
  "telephone number": "_REQUESTED_",
  "telephone": "_REQUESTED_",
  "phone number": "_REQUESTED_",
  "number": "_REQUESTED_",
  "phone": "_REQUESTED_",
  "price range": "_REQUESTED_",
  "price": "_REQUESTED_",
  "range of price": "_REQUESTED_",
  "cost": "_REQUESTED_",
  "pricerange": "_REQUESTED_",
  "postal code": "_REQUESTED_",
  "area code": "_REQUESTED_",
  "post code": "_REQUESTED_",
  "postcode": "_REQUESTED_",
  "signature plate": "_REQUESTED_",
  "special dish": "_REQUESTED_",
  "special plate": "_REQUESTED_",
  "specialty": "_REQUESTED_",
  "signature dish": "_REQUESTED_",
  "specialized": "_REQUESTED_",
  "called": "_REQUESTED_",
  "name": "_REQUESTED_",
  "affordable": "moderate",
  "not too expensive": "moderate",
  "moderately": "moderate",
  "high priced": "expensive",
  "middle-eastern": "middle eastern",
  "middleeastern": "middle eastern",
  "sea food": "seafood",
  "center": "centre",
  "dont care": "dontcare",
  "don't care": "dontcare",
  "do not care": "dontcare",
  "does not matter": "dontcare",
  "doesnt matter": "dontcare",
  "doesn't matter": "dontcare",
  "not important": "dontcare",
  "anywhere": "dontcare",
  "any": "dontcare",
  "dont mind": "dontcare",
  "american": "north american",
  "usa": "north american",
  "us": "north american",
  "belgium": "belgian",
  "barbecue": "barbeque",
  "pan asian": "asian oriental",
  "steak house": "steakhouse",
  "australian asian": "australasian",
  "pizza hut": "pizza hut city centre",
  "how much": "_REQUESTED_"
}